basicnumeriq/__init__.py
basicnumeriq/operations.py
basicnumeriq-0.0.3.dist-info/LICENSE
basicnumeriq-0.0.3.dist-info/METADATA
basicnumeriq-0.0.3.dist-info/WHEEL
basicnumeriq-0.0.3.dist-info/top_level.txt
basicnumeriq-0.0.3.dist-info/RECORD
