Metadata-Version: 2.2
Name: basicnumeriq
Version: 0.0.3
Summary: A simple math operations library.
Home-page: https://github.com/furkankarakuz/basicnumeriq
Author: furkankarakuz
Classifier: Programming Language :: Python :: 3
Classifier: License :: OSI Approved :: Apache Software License
Classifier: Operating System :: OS Independent
Requires-Python: >=3.10
License-File: LICENSE
Dynamic: author
Dynamic: classifier
Dynamic: description
Dynamic: description-content-type
Dynamic: home-page
Dynamic: requires-python
Dynamic: summary
